public final strange1(Lorg/openjdk/jmh/logic/BlackHole;)V
  @Lorg/openjdk/jmh/annotations/GenerateMicroBenchmark;()
  @Lorg/openjdk/jmh/annotations/Warmup;(timeUnit=Ljava/util/concurrent/TimeUnit;.SECONDS, time=1, iterations=3)
  @Lorg/openjdk/jmh/annotations/Measurement;(timeUnit=Ljava/util/concurrent/TimeUnit;.SECONDS, time=1, iterations=3)
  @Lorg/jetbrains/annotations/NotNull;() // invisible
    @Lorg/jetbrains/annotations/NotNull;() // invisible, parameter 0
    @Ljet/runtime/typeinfo/JetValueParameter;(name="bh") // parameter 0
   L0
   L1
    ALOAD 1
    LDC "bh"
    INVOKESTATIC kotlin/jvm/internal/Intrinsics.checkParameterIsNotNull (Ljava/lang/Object;Ljava/lang/String;)V
   L2
    LINENUMBER 102 L2
    ALOAD 1
    ALOAD 0
    ALOAD 0
    GETFIELD ru/benchmark/functional/InliningString.objects : Ljava/util/ArrayList;
    CHECKCAST java/lang/Iterable
    GETSTATIC ru/benchmark/functional/InliningString$strange1$1.instance$ : Lru/benchmark/functional/InliningString$strange1$1;
    CHECKCAST kotlin/Function0
    INVOKEVIRTUAL ru/benchmark/functional/InliningString.fun1 (Ljava/lang/Iterable;Lkotlin/Function0;)I
    INVOKEVIRTUAL org/openjdk/jmh/logic/BlackHole.consume (I)V
   L3
    RETURN
   L4
    LOCALVARIABLE this Lru/benchmark/functional/InliningString; L0 L4 0
    LOCALVARIABLE bh Lorg/openjdk/jmh/logic/BlackHole; L0 L4 1
    MAXSTACK = -1
    MAXLOCALS = -1

public final fun1(Ljava/lang/Iterable;Lkotlin/Function0;)I
    @Lorg/jetbrains/annotations/NotNull;() // invisible, parameter 0
    @Lorg/jetbrains/annotations/NotNull;() // invisible, parameter 1
    @Ljet/runtime/typeinfo/JetValueParameter;(name="iter") // parameter 0
    @Ljet/runtime/typeinfo/JetValueParameter;(name="provider") // parameter 1
   L0
   L1
    ALOAD 1
    LDC "iter"
    INVOKESTATIC kotlin/jvm/internal/Intrinsics.checkParameterIsNotNull (Ljava/lang/Object;Ljava/lang/String;)V
    ALOAD 2
    LDC "provider"
    INVOKESTATIC kotlin/jvm/internal/Intrinsics.checkParameterIsNotNull (Ljava/lang/Object;Ljava/lang/String;)V
   L2
   L3
    LINENUMBER 113 L3
    ICONST_0
    ISTORE 3
   L4
    LINENUMBER 114 L4
    ALOAD 1
    INVOKEINTERFACE java/lang/Iterable.iterator ()Ljava/util/Iterator;
    ASTORE 5
   L5
    ALOAD 5
    INVOKEINTERFACE java/util/Iterator.hasNext ()Z
    IFEQ L6
   L7
    ALOAD 5
    INVOKEINTERFACE java/util/Iterator.next ()Ljava/lang/Object;
    CHECKCAST java/lang/String
    ASTORE 4
   L8
    LINENUMBER 115 L8
    ILOAD 3
    ALOAD 2
    INVOKEINTERFACE kotlin/Function0.invoke ()Ljava/lang/Object;
    CHECKCAST java/lang/Number
    INVOKEVIRTUAL java/lang/Number.intValue ()I
    IADD
    ISTORE 3
   L9
   L10
    GOTO L5
   L6
    LOCALVARIABLE i Ljava/lang/String; L7 L10 4
   L11
    LINENUMBER 116 L11
    ILOAD 3
    IRETURN
   L12
    LOCALVARIABLE sum I L2 L12 3
   L13
    LOCALVARIABLE this Lru/benchmark/functional/InliningString; L0 L13 0
    LOCALVARIABLE iter Ljava/lang/Iterable; L0 L13 1
    LOCALVARIABLE provider Lkotlin/Function0; L0 L13 2
    MAXSTACK = -1
    MAXLOCALS = -1